ckip.py
ckip_segmenter-1.0.2.dist-info/DESCRIPTION.rst
ckip_segmenter-1.0.2.dist-info/METADATA
ckip_segmenter-1.0.2.dist-info/RECORD
ckip_segmenter-1.0.2.dist-info/WHEEL
ckip_segmenter-1.0.2.dist-info/metadata.json
ckip_segmenter-1.0.2.dist-info/top_level.txt
